{"keys": ["", "13805", "13670", "13698", "13672", "13822", "14372", "13831", "13832", "13833", "13834", "13792", "109048", "13681", "13667", "13809", "109467", "13666", "13949", "13955", "13879", "109466", "109532", "13979", "109522", "13665", "13806", "13664", "14548", "13892", "109490", "14549", "13950", "13663", "13938", "13888", "109047", "13662", "13661", "13808", "13890", "14432", "109495", "13893", "13807", "13885", "13659", "13690", "13660", "13658", "13882", "13884", "13899", "13894", "13682", "13973", "13683", "13668", "109051", "109052", "13947", "13946", "13993", "13669", "13915", "13723", "13984", "13929", "13974", "13684", "13674", "109501", "13905", "13930", "13910", "13983", "13906", "13904", "13931", "13676", "13907", "109502", "13903", "13911", "13920", "13912", "13902", "13921", "13913", "13924", "13919", "13923", "13922"], "data": {"13834": {"adresa": "Vodnick\u00e1 337, \u00dajezd", "Count_": 0, "firem_m2": 0, "PocetPodla": 1, "PocetBytu": 1, "ZastavenaP": 0, "PodlahovaP": 0}, "13831": {"adresa": "Vodnick\u00e1 334, \u00dajezd", "Count_": 0, "firem_m2": 0, "PocetPodla": 1, "PocetBytu": 2, "ZastavenaP": 0, "PodlahovaP": 0}, "13832": {"adresa": "Vodnick\u00e1 335, \u00dajezd", "Count_": 0, "firem_m2": 0, "PocetPodla": 1, "PocetBytu": 1, "ZastavenaP": 0, "PodlahovaP": 0}, "13833": {"adresa": "Vodnick\u00e1 336, \u00dajezd", "Count_": 0, "firem_m2": 0, "PocetPodla": 1, "PocetBytu": 1, "ZastavenaP": 0, "PodlahovaP": 0}, "13938": {"adresa": "Stud\u00e1nkov\u00e1 492, \u00dajezd", "Count_": 0, "firem_m2": 0, "PocetPodla": 2, "PocetBytu": 1, "ZastavenaP": 138, "PodlahovaP": 198}, "13931": {"adresa": "Pastevc\u016f 484, \u00dajezd", "Count_": 4, "firem_m2": 0, "PocetPodla": 5, "PocetBytu": 3, "ZastavenaP": 0, "PodlahovaP": 0}, "13930": {"adresa": "Pastevc\u016f 475, \u00dajezd", "Count_": 1, "firem_m2": 0.000917431192661, "PocetPodla": 4, "PocetBytu": 10, "ZastavenaP": 833, "PodlahovaP": 1090}, "109051": {"adresa": "Formansk\u00e1 225, \u00dajezd", "Count_": 0, "firem_m2": 0, "PocetPodla": 0, "PocetBytu": 0, "ZastavenaP": 0, "PodlahovaP": 0}, "109052": {"adresa": "Formansk\u00e1 226, \u00dajezd", "Count_": 0, "firem_m2": 0, "PocetPodla": 0, "PocetBytu": 0, "ZastavenaP": 0, "PodlahovaP": 0}, "109466": {"adresa": "Pod nap\u011bt\u00edm 294, \u00dajezd", "Count_": 0, "firem_m2": 0, "PocetPodla": 0, "PocetBytu": 0, "ZastavenaP": 0, "PodlahovaP": 0}, "13921": {"adresa": "U louky 486, \u00dajezd", "Count_": 4, "firem_m2": 0, "PocetPodla": 5, "PocetBytu": 28, "ZastavenaP": 1527, "PodlahovaP": 0}, "14549": {"adresa": "Vodnick\u00e1 531, \u00dajezd", "Count_": 3, "firem_m2": 0.00588235294118, "PocetPodla": 0, "PocetBytu": 2, "ZastavenaP": 275, "PodlahovaP": 510}, "14548": {"adresa": "Vodnick\u00e1 530, \u00dajezd", "Count_": 1, "firem_m2": 0.00180505415162, "PocetPodla": 0, "PocetBytu": 0, "ZastavenaP": 353, "PodlahovaP": 554}, "109502": {"adresa": "Formansk\u00e1 478, \u00dajezd", "Count_": 0, "firem_m2": 0, "PocetPodla": 0, "PocetBytu": 0, "ZastavenaP": 0, "PodlahovaP": 0}, "109501": {"adresa": "Formansk\u00e1 478, \u00dajezd", "Count_": 0, "firem_m2": 0, "PocetPodla": 0, "PocetBytu": 0, "ZastavenaP": 0, "PodlahovaP": 0}, "13723": {"adresa": "Formansk\u00e1 255, \u00dajezd", "Count_": 0, "firem_m2": 0, "PocetPodla": 1, "PocetBytu": 1, "ZastavenaP": 0, "PodlahovaP": 0}, "13929": {"adresa": "Pastevc\u016f 474, \u00dajezd", "Count_": 1, "firem_m2": 0.0013698630137, "PocetPodla": 4, "PocetBytu": 11, "ZastavenaP": 243, "PodlahovaP": 730}, "13683": {"adresa": "Formansk\u00e1 226, \u00dajezd", "Count_": 0, "firem_m2": 0, "PocetPodla": 1, "PocetBytu": 1, "ZastavenaP": 0, "PodlahovaP": 0}, "13682": {"adresa": "Formansk\u00e1 225, \u00dajezd", "Count_": 0, "firem_m2": 0, "PocetPodla": 1, "PocetBytu": 1, "ZastavenaP": 0, "PodlahovaP": 0}, "13924": {"adresa": "Pastevc\u016f 490, \u00dajezd", "Count_": 0, "firem_m2": 0, "PocetPodla": 5, "PocetBytu": 11, "ZastavenaP": 240, "PodlahovaP": 0}, "13922": {"adresa": "Pastevc\u016f 488, \u00dajezd", "Count_": 1, "firem_m2": 0, "PocetPodla": 5, "PocetBytu": 14, "ZastavenaP": 225, "PodlahovaP": 0}, "13923": {"adresa": "Pastevc\u016f 489, \u00dajezd", "Count_": 0, "firem_m2": 0, "PocetPodla": 5, "PocetBytu": 14, "ZastavenaP": 240, "PodlahovaP": 0}, "13920": {"adresa": "U louky 485, \u00dajezd", "Count_": 5, "firem_m2": 0, "PocetPodla": 5, "PocetBytu": 14, "ZastavenaP": 352, "PodlahovaP": 0}, "13684": {"adresa": "Formansk\u00e1 227, \u00dajezd", "Count_": 0, "firem_m2": 0, "PocetPodla": 1, "PocetBytu": 1, "ZastavenaP": 0, "PodlahovaP": 0}, "13690": {"adresa": "Formansk\u00e1 233, \u00dajezd", "Count_": 1, "firem_m2": 0, "PocetPodla": 1, "PocetBytu": 1, "ZastavenaP": 0, "PodlahovaP": 0}, "13698": {"adresa": "Formansk\u00e1 242, \u00dajezd", "Count_": 1, "firem_m2": 0, "PocetPodla": 1, "PocetBytu": 1, "ZastavenaP": 0, "PodlahovaP": 0}, "13919": {"adresa": "Pastevc\u016f 483, \u00dajezd", "Count_": 1, "firem_m2": 0, "PocetPodla": 1, "PocetBytu": 28, "ZastavenaP": 0, "PodlahovaP": 0}, "13913": {"adresa": "Pastevc\u016f 473, \u00dajezd", "Count_": 1, "firem_m2": 0, "PocetPodla": 5, "PocetBytu": 10, "ZastavenaP": 0, "PodlahovaP": 0}, "13912": {"adresa": "Pastevc\u016f 472, \u00dajezd", "Count_": 0, "firem_m2": 0, "PocetPodla": 3, "PocetBytu": 10, "ZastavenaP": 0, "PodlahovaP": 0}, "13911": {"adresa": "Pastevc\u016f 471, \u00dajezd", "Count_": 2, "firem_m2": 0, "PocetPodla": 4, "PocetBytu": 10, "ZastavenaP": 0, "PodlahovaP": 0}, "13910": {"adresa": "Formansk\u00e1 478, \u00dajezd", "Count_": 0, "firem_m2": 0, "PocetPodla": 3, "PocetBytu": 2, "ZastavenaP": 134, "PodlahovaP": 0}, "13915": {"adresa": "Stud\u00e1nkov\u00e1 480, \u00dajezd", "Count_": 1, "firem_m2": 0, "PocetPodla": 1, "PocetBytu": 1, "ZastavenaP": 0, "PodlahovaP": 0}, "13993": {"adresa": "Pastevc\u016f 526, \u00dajezd", "Count_": 0, "firem_m2": 0, "PocetPodla": 2, "PocetBytu": 1, "ZastavenaP": 139, "PodlahovaP": 210}, "13904": {"adresa": "Rem\u00edzkov\u00e1 467, \u00dajezd", "Count_": 0, "firem_m2": 0, "PocetPodla": 4, "PocetBytu": 14, "ZastavenaP": 0, "PodlahovaP": 0}, "13905": {"adresa": "Pastevc\u016f 468, \u00dajezd", "Count_": 1, "firem_m2": 0, "PocetPodla": 3, "PocetBytu": 11, "ZastavenaP": 0, "PodlahovaP": 0}, "13906": {"adresa": "Pastevc\u016f 469, \u00dajezd", "Count_": 3, "firem_m2": 0, "PocetPodla": 5, "PocetBytu": 28, "ZastavenaP": 0, "PodlahovaP": 0}, "13907": {"adresa": "Pastevc\u016f 470, \u00dajezd", "Count_": 0, "firem_m2": 0, "PocetPodla": 1, "PocetBytu": 14, "ZastavenaP": 0, "PodlahovaP": 0}, "13902": {"adresa": "Kate\u0159insk\u00e9 n\u00e1m\u011bst\u00ed 465, \u00dajezd", "Count_": 0, "firem_m2": 0, "PocetPodla": 0, "PocetBytu": 10, "ZastavenaP": 0, "PodlahovaP": 0}, "13903": {"adresa": "Rem\u00edzkov\u00e1 466, \u00dajezd", "Count_": 1, "firem_m2": 0, "PocetPodla": 5, "PocetBytu": 28, "ZastavenaP": 0, "PodlahovaP": 0}, "13669": {"adresa": "Formansk\u00e1 212, \u00dajezd", "Count_": 0, "firem_m2": 0, "PocetPodla": 1, "PocetBytu": 1, "ZastavenaP": 0, "PodlahovaP": 0}, "13668": {"adresa": "Formansk\u00e1 211, \u00dajezd", "Count_": 0, "firem_m2": 0, "PocetPodla": 1, "PocetBytu": 1, "ZastavenaP": 0, "PodlahovaP": 0}, "13661": {"adresa": "Formansk\u00e1 204, \u00dajezd", "Count_": 0, "firem_m2": 0, "PocetPodla": 1, "PocetBytu": 1, "ZastavenaP": 0, "PodlahovaP": 0}, "13660": {"adresa": "Formansk\u00e1 203, \u00dajezd", "Count_": 0, "firem_m2": 0, "PocetPodla": 1, "PocetBytu": 1, "ZastavenaP": 0, "PodlahovaP": 0}, "13663": {"adresa": "Formansk\u00e1 206, \u00dajezd", "Count_": 0, "firem_m2": 0, "PocetPodla": 1, "PocetBytu": 1, "ZastavenaP": 0, "PodlahovaP": 0}, "13662": {"adresa": "Formansk\u00e1 205, \u00dajezd", "Count_": 0, "firem_m2": 0, "PocetPodla": 1, "PocetBytu": 1, "ZastavenaP": 0, "PodlahovaP": 0}, "13665": {"adresa": "Formansk\u00e1 208, \u00dajezd", "Count_": 0, "firem_m2": 0, "PocetPodla": 1, "PocetBytu": 1, "ZastavenaP": 0, "PodlahovaP": 0}, "13664": {"adresa": "Formansk\u00e1 207, \u00dajezd", "Count_": 0, "firem_m2": 0, "PocetPodla": 1, "PocetBytu": 1, "ZastavenaP": 0, "PodlahovaP": 0}, "13667": {"adresa": "Formansk\u00e1 210, \u00dajezd", "Count_": 0, "firem_m2": 0, "PocetPodla": 1, "PocetBytu": 1, "ZastavenaP": 0, "PodlahovaP": 0}, "13983": {"adresa": "Pastevc\u016f 524, \u00dajezd", "Count_": 1, "firem_m2": 0.00327868852459, "PocetPodla": 2, "PocetBytu": 1, "ZastavenaP": 207, "PodlahovaP": 305}, "13879": {"adresa": "Vodnick\u00e1 454, \u00dajezd", "Count_": 0, "firem_m2": 0, "PocetPodla": 1, "PocetBytu": 1, "ZastavenaP": 0, "PodlahovaP": 0}, "13973": {"adresa": "Pastevc\u016f 520, \u00dajezd", "Count_": 0, "firem_m2": 0, "PocetPodla": 3, "PocetBytu": 1, "ZastavenaP": 121, "PodlahovaP": 240}, "13974": {"adresa": "Pastevc\u016f 521, \u00dajezd", "Count_": 0, "firem_m2": 0, "PocetPodla": 0, "PocetBytu": 1, "ZastavenaP": 0, "PodlahovaP": 0}, "13979": {"adresa": "Stud\u00e1nkov\u00e1 522, \u00dajezd", "Count_": 2, "firem_m2": 0, "PocetPodla": 1, "PocetBytu": 1, "ZastavenaP": 0, "PodlahovaP": 0}, "109495": {"adresa": "Stud\u00e1nkov\u00e1 461, \u00dajezd", "Count_": 0, "firem_m2": 0, "PocetPodla": 0, "PocetBytu": 0, "ZastavenaP": 0, "PodlahovaP": 0}, "13681": {"adresa": "Formansk\u00e1 224, \u00dajezd", "Count_": 0, "firem_m2": 0, "PocetPodla": 1, "PocetBytu": 1, "ZastavenaP": 0, "PodlahovaP": 0}, "14432": {"adresa": "Stud\u00e1nkov\u00e1 395, \u00dajezd", "Count_": 1, "firem_m2": 0, "PocetPodla": 1, "PocetBytu": 1, "ZastavenaP": 0, "PodlahovaP": 0}, "13672": {"adresa": "Formansk\u00e1 215, \u00dajezd", "Count_": 0, "firem_m2": 0, "PocetPodla": 1, "PocetBytu": 1, "ZastavenaP": 0, "PodlahovaP": 0}, "109490": {"adresa": "Stud\u00e1nkov\u00e1 459, \u00dajezd", "Count_": 0, "firem_m2": 0, "PocetPodla": 0, "PocetBytu": 0, "ZastavenaP": 0, "PodlahovaP": 0}, "13670": {"adresa": "Formansk\u00e1 213, \u00dajezd", "Count_": 0, "firem_m2": 0, "PocetPodla": 1, "PocetBytu": 1, "ZastavenaP": 0, "PodlahovaP": 0}, "13676": {"adresa": "Formansk\u00e1 219, \u00dajezd", "Count_": 0, "firem_m2": 0, "PocetPodla": 2, "PocetBytu": 1, "ZastavenaP": 301, "PodlahovaP": 375}, "13674": {"adresa": "Formansk\u00e1 217, \u00dajezd", "Count_": 0, "firem_m2": 0, "PocetPodla": 1, "PocetBytu": 1, "ZastavenaP": 0, "PodlahovaP": 0}, "13809": {"adresa": "Pod nap\u011bt\u00edm 294, \u00dajezd", "Count_": 0, "firem_m2": 0, "PocetPodla": 1, "PocetBytu": 1, "ZastavenaP": 0, "PodlahovaP": 0}, "13808": {"adresa": "Formansk\u00e1 293, \u00dajezd", "Count_": 0, "firem_m2": 0, "PocetPodla": 1, "PocetBytu": 1, "ZastavenaP": 0, "PodlahovaP": 0}, "13805": {"adresa": "Formansk\u00e1 289, \u00dajezd", "Count_": 1, "firem_m2": 0, "PocetPodla": 1, "PocetBytu": 1, "ZastavenaP": 0, "PodlahovaP": 0}, "13807": {"adresa": "Formansk\u00e1 292, \u00dajezd", "Count_": 1, "firem_m2": 0, "PocetPodla": 1, "PocetBytu": 0, "ZastavenaP": 0, "PodlahovaP": 0}, "13806": {"adresa": "Formansk\u00e1 291, \u00dajezd", "Count_": 0, "firem_m2": 0, "PocetPodla": 1, "PocetBytu": 1, "ZastavenaP": 0, "PodlahovaP": 0}, "13885": {"adresa": "Stud\u00e1nkov\u00e1 450, \u00dajezd", "Count_": 0, "firem_m2": 0, "PocetPodla": 1, "PocetBytu": 1, "ZastavenaP": 0, "PodlahovaP": 0}, "13884": {"adresa": "Stud\u00e1nkov\u00e1 458, \u00dajezd", "Count_": 0, "firem_m2": 0, "PocetPodla": 1, "PocetBytu": 1, "ZastavenaP": 0, "PodlahovaP": 0}, "13882": {"adresa": "Stud\u00e1nkov\u00e1 456, \u00dajezd", "Count_": 3, "firem_m2": 0, "PocetPodla": 1, "PocetBytu": 1, "ZastavenaP": 0, "PodlahovaP": 0}, "13888": {"adresa": "Stud\u00e1nkov\u00e1 459, \u00dajezd", "Count_": 0, "firem_m2": 0, "PocetPodla": 1, "PocetBytu": 1, "ZastavenaP": 0, "PodlahovaP": 0}, "13984": {"adresa": "Pastevc\u016f 525, \u00dajezd", "Count_": 0, "firem_m2": 0, "PocetPodla": 3, "PocetBytu": 1, "ZastavenaP": 206, "PodlahovaP": 280}, "109532": {"adresa": "Formansk\u00e1 7, \u00dajezd", "Count_": 0, "firem_m2": 0, "PocetPodla": 0, "PocetBytu": 0, "ZastavenaP": 0, "PodlahovaP": 0}, "13792": {"adresa": "Pod nap\u011bt\u00edm 274, \u00dajezd", "Count_": 2, "firem_m2": 0, "PocetPodla": 1, "PocetBytu": 1, "ZastavenaP": 0, "PodlahovaP": 0}, "109467": {"adresa": "Pod nap\u011bt\u00edm 294, \u00dajezd", "Count_": 0, "firem_m2": 0, "PocetPodla": 0, "PocetBytu": 0, "ZastavenaP": 0, "PodlahovaP": 0}, "13955": {"adresa": "Formansk\u00e1 7, \u00dajezd", "Count_": 0, "firem_m2": 0, "PocetPodla": 0, "PocetBytu": 0, "ZastavenaP": 0, "PodlahovaP": 0}, "13950": {"adresa": "Stud\u00e1nkov\u00e1 515, \u00dajezd", "Count_": 0, "firem_m2": 0, "PocetPodla": 1, "PocetBytu": 1, "ZastavenaP": 139, "PodlahovaP": 118}, "13658": {"adresa": "Formansk\u00e1 201, \u00dajezd", "Count_": 0, "firem_m2": 0, "PocetPodla": 1, "PocetBytu": 1, "ZastavenaP": 0, "PodlahovaP": 0}, "13659": {"adresa": "Formansk\u00e1 202, \u00dajezd", "Count_": 1, "firem_m2": 0, "PocetPodla": 1, "PocetBytu": 1, "ZastavenaP": 0, "PodlahovaP": 0}, "13666": {"adresa": "Formansk\u00e1 209, \u00dajezd", "Count_": 0, "firem_m2": 0, "PocetPodla": 1, "PocetBytu": 1, "ZastavenaP": 0, "PodlahovaP": 0}, "13894": {"adresa": "Stud\u00e1nkov\u00e1 462, \u00dajezd", "Count_": 1, "firem_m2": 0, "PocetPodla": 1, "PocetBytu": 1, "ZastavenaP": 0, "PodlahovaP": 0}, "13892": {"adresa": "Stud\u00e1nkov\u00e1 449, \u00dajezd", "Count_": 0, "firem_m2": 0, "PocetPodla": 2, "PocetBytu": 1, "ZastavenaP": 186, "PodlahovaP": 0}, "13893": {"adresa": "Stud\u00e1nkov\u00e1 461, \u00dajezd", "Count_": 0, "firem_m2": 0, "PocetPodla": 1, "PocetBytu": 1, "ZastavenaP": 0, "PodlahovaP": 0}, "13890": {"adresa": "Stud\u00e1nkov\u00e1 448, \u00dajezd", "Count_": 0, "firem_m2": 0, "PocetPodla": 1, "PocetBytu": 1, "ZastavenaP": 0, "PodlahovaP": 0}, "13899": {"adresa": "Stud\u00e1nkov\u00e1 477, \u00dajezd", "Count_": 2, "firem_m2": 0, "PocetPodla": 2, "PocetBytu": 1, "ZastavenaP": 107, "PodlahovaP": 0}, "13949": {"adresa": "Stud\u00e1nkov\u00e1 514, \u00dajezd", "Count_": 1, "firem_m2": 0.00363636363636, "PocetPodla": 2, "PocetBytu": 1, "ZastavenaP": 193, "PodlahovaP": 275}, "109522": {"adresa": "Stud\u00e1nkov\u00e1 514, \u00dajezd", "Count_": 0, "firem_m2": 0, "PocetPodla": 0, "PocetBytu": 0, "ZastavenaP": 0, "PodlahovaP": 0}, "13946": {"adresa": "Pastevc\u016f 511, \u00dajezd", "Count_": 0, "firem_m2": 0, "PocetPodla": 3, "PocetBytu": 2, "ZastavenaP": 0, "PodlahovaP": 0}, "13947": {"adresa": "Pastevc\u016f 510, \u00dajezd", "Count_": 1, "firem_m2": 0.0030303030303, "PocetPodla": 4, "PocetBytu": 2, "ZastavenaP": 101, "PodlahovaP": 330}, "14372": {"adresa": "Vodnick\u00e1 319, \u00dajezd", "Count_": 0, "firem_m2": 0, "PocetPodla": 1, "PocetBytu": 1, "ZastavenaP": 0, "PodlahovaP": 0}, "13822": {"adresa": "Vodnick\u00e1 317, \u00dajezd", "Count_": 0, "firem_m2": 0, "PocetPodla": 4, "PocetBytu": 1, "ZastavenaP": 95, "PodlahovaP": 315}, "109048": {"adresa": "Formansk\u00e1 213, \u00dajezd", "Count_": 0, "firem_m2": 0, "PocetPodla": 0, "PocetBytu": 0, "ZastavenaP": 0, "PodlahovaP": 0}, "109047": {"adresa": "Formansk\u00e1 208, \u00dajezd", "Count_": 0, "firem_m2": 0, "PocetPodla": 0, "PocetBytu": 0, "ZastavenaP": 0, "PodlahovaP": 0}}, "grid": ["            !!        #      $   %              &  ''     ())**+", ",           !!           -  $$$ %                 '''        *++", ",,              .        -   $ %%          /       '          + ", ",   0011       ..                       ////2                   ", "   000   333       44                  ///2 2  555              ", " 6 00     33      7                    22      555              ", "       8   99     7                      :       5              ", "      88    9            ;;             :: <               =    ", "  >>                 ?   ;;               <<             ====  @", " >>>>        A          ;;;                BB          ===== @@@", "C >        AAA     DD    ;           EE   BB FF   GG    ==  @@@@", "C            A     DD        HHH           FFF  GG              ", "               II   D        HHH          FF GGG                ", "     JJ        II        K L     M        FGGG                  ", "     JJ                N  LLL   MM                              ", "                      NN   L    MM              OO              ", "                       NN           P      Q  OOO RRR           ", "                  SSS  NN          PP         O RRRRR           ", "                T  S                P         RRR  RR           ", "U            V TT                     WW      R                 ", "U           VV T        XX           WWWY      ZZ               ", "            VV          XX           []YY     ZZZ               ", "                     ^_        ``    ]         Z aa             ", "       bbbb          ^^_       ``         cc    aa              ", "       bbbb       dd ^^                  cc                     ", "             e   dddd     fff            cgg            hh     i", "            ee   ddd       ff             ggg  j    h hhh     ii", "           eeee       kk                   g  jjj   hhhh     l  ", "            ee       kkk     mmm              jjj    h     lll  ", "                     kkkk    mmm               jj           l   ", "                      k                    nn      o            ", "                         pp               nnnn    ooo         qq", "                        pppp       rrr   nnnn    oooo     sss  q", "                        pppp      rrrr   nnnn    oooo           ", "                         ppp      rrrr  nnnn       o            ", "                          p             nnn    tt               ", "                                        nn    tttt              ", "                                uu            tttt          vv  ", "                               uuuu          tttt          vvvv ", "                                uu           ttt           vvv  ", "                                     ww       t            vvv  ", "                                     www          xxx    y  v   ", "                                     www  zz     xxxx   yyy     ", "                                          zzz     xx   yyyy     ", "                                         zzz       x   yyyy     ", "                                                {     yyyy    ||", "                                               {{{    yyy    |||", "                                               {{{     y    ||||", "                                                {   }      |||| ", "                                                   }}}     |||  ", "                                                   }}}     ||   ", "                                                    }   ~   |   ", "                                                       ~~~      ", "                                                       ~~~      ", "                                                        ~       ", "                                                                ", "                                                                ", "                                                                ", "                                                                ", "                                                                ", "                                                                ", "                                                                ", "                                                                ", "                                                                "]}