{"keys": ["", "42980", "42979", "42978", "42977", "42976", "42975", "43241", "42595", "99649", "42972", "42969", "42968", "42967", "99656", "99657", "99658", "42986", "42598", "42985", "42987", "43269", "42988", "42952", "99650", "99178", "72245", "72973", "72222", "72853", "72223", "72224", "72854", "72246", "99170", "99169", "73064", "72870", "72858", "72228", "72489"], "data": {"99170": {"adresa": "Le\u0161ensk\u00e1 536, Troja", "Count_": 0, "firem_m2": 0, "PocetPodla": 0, "PocetBytu": 0, "ZastavenaP": 0, "PodlahovaP": 0}, "99169": {"adresa": "Le\u0161ensk\u00e1 536, Troja", "Count_": 0, "firem_m2": 0, "PocetPodla": 0, "PocetBytu": 0, "ZastavenaP": 0, "PodlahovaP": 0}, "72853": {"adresa": "Krosensk\u00e1 533, Troja", "Count_": 0, "firem_m2": 0, "PocetPodla": 0, "PocetBytu": 49, "ZastavenaP": 0, "PodlahovaP": 0}, "99658": {"adresa": "Pozna\u0148sk\u00e1 467, Bohnice", "Count_": 0, "firem_m2": 0, "PocetPodla": 0, "PocetBytu": 0, "ZastavenaP": 0, "PodlahovaP": 0}, "99650": {"adresa": "Vratislavsk\u00e1 398, Bohnice", "Count_": 0, "firem_m2": 0, "PocetPodla": 0, "PocetBytu": 0, "ZastavenaP": 0, "PodlahovaP": 0}, "99656": {"adresa": "Pozna\u0148sk\u00e1 428, Bohnice", "Count_": 0, "firem_m2": 0, "PocetPodla": 0, "PocetBytu": 0, "ZastavenaP": 0, "PodlahovaP": 0}, "99657": {"adresa": "Pozna\u0148sk\u00e1 460, Bohnice", "Count_": 0, "firem_m2": 0, "PocetPodla": 0, "PocetBytu": 0, "ZastavenaP": 0, "PodlahovaP": 0}, "42968": {"adresa": "Pozna\u0148sk\u00e1 429, Bohnice", "Count_": 0, "firem_m2": 0, "PocetPodla": 13, "PocetBytu": 36, "ZastavenaP": 0, "PodlahovaP": 0}, "42969": {"adresa": "Pozna\u0148sk\u00e1 430, Bohnice", "Count_": 2, "firem_m2": 0, "PocetPodla": 13, "PocetBytu": 36, "ZastavenaP": 0, "PodlahovaP": 0}, "72222": {"adresa": "Krosensk\u00e1 531, Troja", "Count_": 6, "firem_m2": 0, "PocetPodla": 0, "PocetBytu": 48, "ZastavenaP": 0, "PodlahovaP": 0}, "72223": {"adresa": "Le\u0161ensk\u00e1 535, Troja", "Count_": 2, "firem_m2": 0, "PocetPodla": 8, "PocetBytu": 25, "ZastavenaP": 0, "PodlahovaP": 0}, "72224": {"adresa": "Le\u0161ensk\u00e1 536, Troja", "Count_": 10, "firem_m2": 0, "PocetPodla": 8, "PocetBytu": 24, "ZastavenaP": 0, "PodlahovaP": 0}, "72870": {"adresa": "Sosnoveck\u00e1 578, Troja", "Count_": 2, "firem_m2": 0, "PocetPodla": 12, "PocetBytu": 33, "ZastavenaP": 0, "PodlahovaP": 0}, "72854": {"adresa": "Le\u0161ensk\u00e1 537, Troja", "Count_": 18, "firem_m2": 0, "PocetPodla": 0, "PocetBytu": 48, "ZastavenaP": 0, "PodlahovaP": 0}, "72228": {"adresa": "Le\u0161ensk\u00e1 546, Troja", "Count_": 4, "firem_m2": 0, "PocetPodla": 0, "PocetBytu": 126, "ZastavenaP": 0, "PodlahovaP": 0}, "72858": {"adresa": "Le\u0161ensk\u00e1 548, Troja", "Count_": 1, "firem_m2": 0, "PocetPodla": 2, "PocetBytu": 2, "ZastavenaP": 0, "PodlahovaP": 0}, "42967": {"adresa": "Pozna\u0148sk\u00e1 428, Bohnice", "Count_": 1, "firem_m2": 0, "PocetPodla": 13, "PocetBytu": 36, "ZastavenaP": 0, "PodlahovaP": 0}, "72246": {"adresa": "Ol\u0161t\u00fdnsk\u00e1 607, Troja", "Count_": 71, "firem_m2": 0, "PocetPodla": 1, "PocetBytu": 1, "ZastavenaP": 0, "PodlahovaP": 0}, "72245": {"adresa": "T\u011b\u0161\u00ednsk\u00e1 600, Troja", "Count_": 1, "firem_m2": 0, "PocetPodla": 3, "PocetBytu": 0, "ZastavenaP": 0, "PodlahovaP": 0}, "42986": {"adresa": "Pozna\u0148sk\u00e1 456, Bohnice", "Count_": 1, "firem_m2": 0, "PocetPodla": 0, "PocetBytu": 40, "ZastavenaP": 0, "PodlahovaP": 0}, "42987": {"adresa": "Pozna\u0148sk\u00e1 461, Bohnice", "Count_": 5, "firem_m2": 0, "PocetPodla": 1, "PocetBytu": 0, "ZastavenaP": 0, "PodlahovaP": 0}, "42985": {"adresa": "Pozna\u0148sk\u00e1 446, Bohnice", "Count_": 1, "firem_m2": 0, "PocetPodla": 0, "PocetBytu": 40, "ZastavenaP": 0, "PodlahovaP": 0}, "42980": {"adresa": "Pozna\u0148sk\u00e1 441, Bohnice", "Count_": 2, "firem_m2": 0, "PocetPodla": 13, "PocetBytu": 36, "ZastavenaP": 0, "PodlahovaP": 0}, "99178": {"adresa": "T\u011b\u0161\u00ednsk\u00e1 600, Troja", "Count_": 0, "firem_m2": 0, "PocetPodla": 0, "PocetBytu": 0, "ZastavenaP": 0, "PodlahovaP": 0}, "43269": {"adresa": "Pozna\u0148sk\u00e1 830, Bohnice", "Count_": 0, "firem_m2": 0, "PocetPodla": 1, "PocetBytu": 0, "ZastavenaP": 0, "PodlahovaP": 0}, "42988": {"adresa": "Pozna\u0148sk\u00e1 462, Bohnice", "Count_": 2, "firem_m2": 0, "PocetPodla": 2, "PocetBytu": 2, "ZastavenaP": 0, "PodlahovaP": 0}, "99649": {"adresa": "Vratislavsk\u00e1 386, Bohnice", "Count_": 0, "firem_m2": 0, "PocetPodla": 0, "PocetBytu": 0, "ZastavenaP": 0, "PodlahovaP": 0}, "72489": {"adresa": "Hn\u011bzdensk\u00e1 767, Troja", "Count_": 96, "firem_m2": 0, "PocetPodla": 133, "PocetBytu": 650, "ZastavenaP": 0, "PodlahovaP": 0}, "73064": {"adresa": "Lod\u017esk\u00e1 850, Troja", "Count_": 5, "firem_m2": 0.000190774161548, "PocetPodla": 4, "PocetBytu": 0, "ZastavenaP": 7450, "PodlahovaP": 26209}, "43241": {"adresa": "Lod\u017esk\u00e1 808, Bohnice", "Count_": 0, "firem_m2": 0, "PocetPodla": 1, "PocetBytu": 0, "ZastavenaP": 0, "PodlahovaP": 0}, "42598": {"adresa": "Pozna\u0148sk\u00e1 451, Bohnice", "Count_": 6, "firem_m2": 0, "PocetPodla": 0, "PocetBytu": 40, "ZastavenaP": 0, "PodlahovaP": 0}, "42952": {"adresa": "Vratislavsk\u00e1 396, Bohnice", "Count_": 3, "firem_m2": 0, "PocetPodla": 0, "PocetBytu": 48, "ZastavenaP": 0, "PodlahovaP": 0}, "42979": {"adresa": "Pozna\u0148sk\u00e1 440, Bohnice", "Count_": 1, "firem_m2": 0, "PocetPodla": 13, "PocetBytu": 36, "ZastavenaP": 0, "PodlahovaP": 0}, "42978": {"adresa": "Pozna\u0148sk\u00e1 439, Bohnice", "Count_": 0, "firem_m2": 0, "PocetPodla": 13, "PocetBytu": 36, "ZastavenaP": 0, "PodlahovaP": 0}, "42977": {"adresa": "Pozna\u0148sk\u00e1 438, Bohnice", "Count_": 1, "firem_m2": 0, "PocetPodla": 13, "PocetBytu": 36, "ZastavenaP": 0, "PodlahovaP": 0}, "42976": {"adresa": "Pozna\u0148sk\u00e1 437, Bohnice", "Count_": 1, "firem_m2": 0, "PocetPodla": 13, "PocetBytu": 36, "ZastavenaP": 0, "PodlahovaP": 0}, "42975": {"adresa": "Pozna\u0148sk\u00e1 434, Bohnice", "Count_": 1, "firem_m2": 0, "PocetPodla": 12, "PocetBytu": 33, "ZastavenaP": 0, "PodlahovaP": 0}, "72973": {"adresa": "Ol\u0161t\u00fdnsk\u00e1 733, Troja", "Count_": 1, "firem_m2": 0, "PocetPodla": 7, "PocetBytu": 124, "ZastavenaP": 1432, "PodlahovaP": 0}, "42595": {"adresa": "Lod\u017esk\u00e1 399, Bohnice", "Count_": 4, "firem_m2": 0, "PocetPodla": 2, "PocetBytu": 0, "ZastavenaP": 0, "PodlahovaP": 0}, "42972": {"adresa": "Pozna\u0148sk\u00e1 431, Bohnice", "Count_": 2, "firem_m2": 0, "PocetPodla": 12, "PocetBytu": 33, "ZastavenaP": 0, "PodlahovaP": 0}}, "grid": ["          !!###$$$%%%&&&      '''    (((((           ))))))))  *", "                      &&      '''      +++           ))))))))   ", "                                       +++,,,---...  //)        ", "    0                                    ,,,,---...  ////       ", " 11100                                         ...   ////       ", "111100          22  33333333                                    ", "                22 33333333333 44444444                         ", "                    3333333333 4444444444                       ", "                               4444444444                       ", "                                                                ", "                                                                ", "                                                                ", "                                                                ", "                                                                ", "                                                                ", "                                          5555                  ", "       6666                               5555                  ", "       6666666   777777777777777           555             88888", "       666666    777777777777777                           88888", "                    7777                                   88888", "                                                    999         ", "                                                    999         ", "                                                                ", "                                                                ", "                                                                ", "                                                                ", "                                                                ", "         ::                                                     ", "                                                                ", "                                                                ", "  ;;;;;;;;                                                      ", "  ;;;;;;;;       <<<                                            ", "  ;;;;;;;;      <<<<                                            ", ";;;;;;;;;      <<<<                                             ", ";;;;;;;;;      <<<                                              ", ";;;;;;;;;     <<<<                ===     >>                    ", ";;;;;;;;;     <<<<                ===     >>>      ???          ", "  ;;;;;;;    <<<<<<<              ===     >>>      ???          ", "             <<<<<<<<             ==               ???          ", "               <<<<<<              ==              ?@?          ", "                    <              ===              @@          ", "                                  ===               @@@      A A", "                                                    @@      AAAA", "               BBB                                          AAAA", "               BBBBB                           CCCDD            ", "EEE            BBBBB                           CCDD             ", "EEEEEEEEEEEE   BBBB                            CC D             ", "EEEEEEEEEEEE   BBBB                                             ", "EEEEEEEEEEEE   BBBB                                             ", "EEEEEEEEEEEE   BBBB                                             ", "EEEEEEEEEEEE     BB                                             ", "EEEEEEEEEEEE                                                    ", "EEEEEEEEEEEE                                                    ", "EEEEEEEEEEEE                                                    ", "          EE               FFF                              GGGG", "                           FFF                      HHH     GGGG", "                                                    HHH     GGGG", "                                                    HHH         ", "                                                    HHH         ", "                                                    HHH         ", "                                                    HHH         ", "                                                                ", "IIIIIIII I                                                      ", "IIIIIIIIIIIIIIII                                                "]}